{
  "retcode": 1,
  "retdata": {
    "bank_info": {
      "bank": "宁波银行",
      "branch": "北京分行营业部",
      "channelname": "鼎诚易融",
      "id": "5",
      "remarks": "",
      "repaymentaccount": "天津鼎诚易融国际融资租赁有限公司",
      "repaymentnumber": "7701 0122 0005 99381"
    },
    "list": [
      {
        "adjustmoney": "0",
        "dead_line": "2017-02-20",
        "planid": "191136",
        "plantype": "2",
        "repaymentmny": "70",
        "status": "2"
      },
      {
        "adjustmoney": "-280",
        "dead_line": "2017-02-20",
        "planid": "191137",
        "plantype": "1",
        "repaymentmny": "40280",
        "status": "2"
      }
    ],
    "loan_id": "24976",
    "loan_mny": "40000",
    "loan_mny_str": "4万元",
    "loan_number": "201702160073",
    "loan_time": "1487001600",
    "loan_time_str": "2017-02-14",
    "loanperiod": "30",
    "loanperiod_type": "天",
    "qvdaoname": "鼎诚易融",
    "type": "4"
  },
  "retmsg": "[1]ok",
  "rettoken": "e9ab1d1bb12b2f824df9503ba4f0e4cd"
}